{
  "channel_name": "Boing",
  "date": "2026-02-15",
  "programs": [
    {
      "show_name": "Lo Straordinario Mondo Di Gumball",
      "show_logo": "https://tv-programma.it/wp-content/uploads/2026/02/sample-image.webp",
      "start_time": "2026-02-15 00:00:00",
      "end_time": "2026-02-15 00:00:00",
      "episode_number": "S3 E9",
      "show_category": "Scoperta e avventura",
      "show_description": "Gumball è un simpatico gatto blu combina-guai che ogni giorno vive straordinarie avventure assieme a Darwin, l'amico pesciolino."
    },
    {
      "show_name": "Lo Straordinario Mondo Di Gumball",
      "show_logo": "https://tv-programma.it/wp-content/uploads/2026/02/sample-image.webp",
      "start_time": "2026-02-15 00:00:00",
      "end_time": "2026-02-15 00:15:00",
      "episode_number": "S3 E10",
      "show_category": "Scoperta e avventura",
      "show_description": "Gumball è un simpatico gatto blu combina-guai che ogni giorno vive straordinarie avventure assieme a Darwin, l'amico pesciolino."
    },
    {
      "show_name": "Lo Straordinario Mondo Di Gumball",
      "show_logo": "https://tv-programma.it/wp-content/uploads/2026/02/sample-image.webp",
      "start_time": "2026-02-15 00:15:00",
      "end_time": "2026-02-15 00:25:00",
      "episode_number": "S3 E10",
      "show_category": "Scoperta e avventura",
      "show_description": "Gumball è un simpatico gatto blu combina-guai che ogni giorno vive straordinarie avventure assieme a Darwin, l'amico pesciolino."
    },
    {
      "show_name": "Lo Straordinario Mondo Di Gumball",
      "show_logo": "https://tv-programma.it/wp-content/uploads/2026/02/sample-image.webp",
      "start_time": "2026-02-15 00:25:00",
      "end_time": "2026-02-15 00:35:00",
      "episode_number": "S3 E11",
      "show_category": "Scoperta e avventura",
      "show_description": "Gumball è un simpatico gatto blu combina-guai che ogni giorno vive straordinarie avventure assieme a Darwin, l'amico pesciolino."
    },
    {
      "show_name": "Lo Straordinario Mondo Di Gumball",
      "show_logo": "https://tv-programma.it/wp-content/uploads/2026/02/sample-image.webp",
      "start_time": "2026-02-15 00:35:00",
      "end_time": "2026-02-15 00:45:00",
      "episode_number": "S3 E11",
      "show_category": "Scoperta e avventura",
      "show_description": "Gumball è un simpatico gatto blu combina-guai che ogni giorno vive straordinarie avventure assieme a Darwin, l'amico pesciolino."
    },
    {
      "show_name": "Lo Straordinario Mondo Di Gumball",
      "show_logo": "https://tv-programma.it/wp-content/uploads/2026/02/sample-image.webp",
      "start_time": "2026-02-15 00:45:00",
      "end_time": "2026-02-15 00:55:00",
      "episode_number": "S3 E12",
      "show_category": "Scoperta e avventura",
      "show_description": "Gumball è un simpatico gatto blu combina-guai che ogni giorno vive straordinarie avventure assieme a Darwin, l'amico pesciolino."
    },
    {
      "show_name": "Lo Straordinario Mondo Di Gumball",
      "show_logo": "https://tv-programma.it/wp-content/uploads/2026/02/sample-image.webp",
      "start_time": "2026-02-15 00:55:00",
      "end_time": "2026-02-15 01:05:00",
      "episode_number": "S3 E12",
      "show_category": "Scoperta e avventura",
      "show_description": "Gumball è un simpatico gatto blu combina-guai che ogni giorno vive straordinarie avventure assieme a Darwin, l'amico pesciolino."
    },
    {
      "show_name": "Lo Straordinario Mondo Di Gumball",
      "show_logo": "https://tv-programma.it/wp-content/uploads/2026/02/sample-image.webp",
      "start_time": "2026-02-15 01:05:00",
      "end_time": "2026-02-15 01:15:00",
      "episode_number": "S3 E13",
      "show_category": "",
      "show_description": "I membri della famiglia Watterson hanno avuto una pessima giornata a causa di vicissitudini con Larry. Il ragazzo si licenzia da tutti i lavori causando un'apocalisse in citta'."
    },
    {
      "show_name": "Lo Straordinario Mondo Di Gumball",
      "show_logo": "https://tv-programma.it/wp-content/uploads/2026/02/sample-image.webp",
      "start_time": "2026-02-15 01:15:00",
      "end_time": "2026-02-15 01:30:00",
      "episode_number": "S3 E13",
      "show_category": "",
      "show_description": "Siamo a gennaio e Gumball e' triste perche' il Natale e' finito. Cosi' per ritrovare il buonumore si inventa una festivita' che coinvolge tutta la citta' di Elmore."
    },
    {
      "show_name": "Lo Straordinario Mondo Di Gumball",
      "show_logo": "https://tv-programma.it/wp-content/uploads/2026/02/sample-image.webp",
      "start_time": "2026-02-15 01:30:00",
      "end_time": "2026-02-15 01:40:00",
      "episode_number": "S3 E14",
      "show_category": "",
      "show_description": "La signorina Scimmia non vuole liberare una farfalla chiusa in un barattolo perche' teme il cosiddetto effetto farfalla ma Gumball e Darwin non le prestano ascolto e si scatena di tutto."
    },
    {
      "show_name": "Lo Straordinario Mondo Di Gumball",
      "show_logo": "https://tv-programma.it/wp-content/uploads/2026/02/sample-image.webp",
      "start_time": "2026-02-15 01:40:00",
      "end_time": "2026-02-15 01:50:00",
      "episode_number": "S3 E14",
      "show_category": "",
      "show_description": "Gumball e Darwin si chiedono qual e' il senso della vita e interpellano tutti: da Larry ai genitori da Madre Natura fino ai pianeti ma la risposta piu' profonda l'avranno da Sussie."
    },
    {
      "show_name": "Lo Straordinario Mondo Di Gumball",
      "show_logo": "https://tv-programma.it/wp-content/uploads/2026/02/sample-image.webp",
      "start_time": "2026-02-15 01:50:00",
      "end_time": "2026-02-15 02:00:00",
      "episode_number": "S3 E15",
      "show_category": "Scoperta e avventura",
      "show_description": "Gumball è un simpatico gatto blu combina-guai che ogni giorno vive straordinarie avventure assieme a Darwin, l'amico pesciolino."
    },
    {
      "show_name": "Lo Straordinario Mondo Di Gumball",
      "show_logo": "https://tv-programma.it/wp-content/uploads/2026/02/sample-image.webp",
      "start_time": "2026-02-15 02:00:00",
      "end_time": "2026-02-15 02:10:00",
      "episode_number": "S3 E15",
      "show_category": "Scoperta e avventura",
      "show_description": "Gumball è un simpatico gatto blu combina-guai che ogni giorno vive straordinarie avventure assieme a Darwin, l'amico pesciolino."
    },
    {
      "show_name": "Lo Straordinario Mondo Di Gumball",
      "show_logo": "https://tv-programma.it/wp-content/uploads/2026/02/sample-image.webp",
      "start_time": "2026-02-15 02:10:00",
      "end_time": "2026-02-15 02:20:00",
      "episode_number": "S3 E16",
      "show_category": "Scoperta e avventura",
      "show_description": "Gumball è un simpatico gatto blu combina-guai che ogni giorno vive straordinarie avventure assieme a Darwin, l'amico pesciolino."
    },
    {
      "show_name": "Lo Straordinario Mondo Di Gumball",
      "show_logo": "https://tv-programma.it/wp-content/uploads/2026/02/sample-image.webp",
      "start_time": "2026-02-15 02:20:00",
      "end_time": "2026-02-15 02:30:00",
      "episode_number": "S3 E16",
      "show_category": "Scoperta e avventura",
      "show_description": "Gumball è un simpatico gatto blu combina-guai che ogni giorno vive straordinarie avventure assieme a Darwin, l'amico pesciolino."
    },
    {
      "show_name": "Lo Straordinario Mondo Di Gumball",
      "show_logo": "https://tv-programma.it/wp-content/uploads/2026/02/sample-image.webp",
      "start_time": "2026-02-15 02:30:00",
      "end_time": "2026-02-15 02:40:00",
      "episode_number": "S3 E17",
      "show_category": "Scoperta e avventura",
      "show_description": "Gumball è un simpatico gatto blu combina-guai che ogni giorno vive straordinarie avventure assieme a Darwin, l'amico pesciolino."
    },
    {
      "show_name": "Lo Straordinario Mondo Di Gumball",
      "show_logo": "https://tv-programma.it/wp-content/uploads/2026/02/sample-image.webp",
      "start_time": "2026-02-15 02:40:00",
      "end_time": "2026-02-15 02:55:00",
      "episode_number": "S3 E17",
      "show_category": "Scoperta e avventura",
      "show_description": "Gumball è un simpatico gatto blu combina-guai che ogni giorno vive straordinarie avventure assieme a Darwin, l'amico pesciolino."
    },
    {
      "show_name": "Lo Straordinario Mondo Di Gumball",
      "show_logo": "https://tv-programma.it/wp-content/uploads/2026/02/sample-image.webp",
      "start_time": "2026-02-15 02:55:00",
      "end_time": "2026-02-15 03:05:00",
      "episode_number": "S3 E18",
      "show_category": "Scoperta e avventura",
      "show_description": "Gumball è un simpatico gatto blu combina-guai che ogni giorno vive straordinarie avventure assieme a Darwin, l'amico pesciolino."
    },
    {
      "show_name": "Lo Straordinario Mondo Di Gumball",
      "show_logo": "https://tv-programma.it/wp-content/uploads/2026/02/sample-image.webp",
      "start_time": "2026-02-15 03:05:00",
      "end_time": "2026-02-15 03:15:00",
      "episode_number": "S3 E18",
      "show_category": "Scoperta e avventura",
      "show_description": "Gumball è un simpatico gatto blu combina-guai che ogni giorno vive straordinarie avventure assieme a Darwin, l'amico pesciolino."
    },
    {
      "show_name": "Lo Straordinario Mondo Di Gumball",
      "show_logo": "https://tv-programma.it/wp-content/uploads/2026/02/sample-image.webp",
      "start_time": "2026-02-15 03:15:00",
      "end_time": "2026-02-15 03:25:00",
      "episode_number": "S3 E19",
      "show_category": "Scoperta e avventura",
      "show_description": "Gumball è un simpatico gatto blu combina-guai che ogni giorno vive straordinarie avventure assieme a Darwin, l'amico pesciolino."
    },
    {
      "show_name": "Lo Straordinario Mondo Di Gumball",
      "show_logo": "https://tv-programma.it/wp-content/uploads/2026/02/sample-image.webp",
      "start_time": "2026-02-15 03:25:00",
      "end_time": "2026-02-15 03:35:00",
      "episode_number": "S3 E19",
      "show_category": "Scoperta e avventura",
      "show_description": "Gumball è un simpatico gatto blu combina-guai che ogni giorno vive straordinarie avventure assieme a Darwin, l'amico pesciolino."
    },
    {
      "show_name": "Lo Straordinario Mondo Di Gumball",
      "show_logo": "https://tv-programma.it/wp-content/uploads/2026/02/sample-image.webp",
      "start_time": "2026-02-15 03:35:00",
      "end_time": "2026-02-15 03:45:00",
      "episode_number": "S3 E20",
      "show_category": "Scoperta e avventura",
      "show_description": "Gumball è un simpatico gatto blu combina-guai che ogni giorno vive straordinarie avventure assieme a Darwin, l'amico pesciolino."
    },
    {
      "show_name": "Lo Straordinario Mondo Di Gumball",
      "show_logo": "https://tv-programma.it/wp-content/uploads/2026/02/sample-image.webp",
      "start_time": "2026-02-15 03:45:00",
      "end_time": "2026-02-15 03:55:00",
      "episode_number": "S3 E20",
      "show_category": "Scoperta e avventura",
      "show_description": "Gumball è un simpatico gatto blu combina-guai che ogni giorno vive straordinarie avventure assieme a Darwin, l'amico pesciolino."
    },
    {
      "show_name": "Lo Straordinario Mondo Di Gumball",
      "show_logo": "https://tv-programma.it/wp-content/uploads/2026/02/sample-image.webp",
      "start_time": "2026-02-15 03:55:00",
      "end_time": "2026-02-15 04:10:00",
      "episode_number": "S4 E1",
      "show_category": "Scoperta e avventura",
      "show_description": "Gumball è un simpatico gatto blu combina-guai che ogni giorno vive straordinarie avventure assieme a Darwin, l'amico pesciolino."
    },
    {
      "show_name": "Lo Straordinario Mondo Di Gumball",
      "show_logo": "https://tv-programma.it/wp-content/uploads/2026/02/sample-image.webp",
      "start_time": "2026-02-15 04:10:00",
      "end_time": "2026-02-15 04:20:00",
      "episode_number": "S4 E2",
      "show_category": "Scoperta e avventura",
      "show_description": "Gumball è un simpatico gatto blu combina-guai che ogni giorno vive straordinarie avventure assieme a Darwin, l'amico pesciolino."
    },
    {
      "show_name": "Lo Straordinario Mondo Di Gumball",
      "show_logo": "https://tv-programma.it/wp-content/uploads/2026/02/sample-image.webp",
      "start_time": "2026-02-15 04:20:00",
      "end_time": "2026-02-15 04:30:00",
      "episode_number": "S4 E3",
      "show_category": "Scoperta e avventura",
      "show_description": "Gumball è un simpatico gatto blu combina-guai che ogni giorno vive straordinarie avventure assieme a Darwin, l'amico pesciolino."
    },
    {
      "show_name": "Lo Straordinario Mondo Di Gumball",
      "show_logo": "https://tv-programma.it/wp-content/uploads/2026/02/sample-image.webp",
      "start_time": "2026-02-15 04:30:00",
      "end_time": "2026-02-15 04:40:00",
      "episode_number": "S4 E4",
      "show_category": "Scoperta e avventura",
      "show_description": "Gumball è un simpatico gatto blu combina-guai che ogni giorno vive straordinarie avventure assieme a Darwin, l'amico pesciolino."
    },
    {
      "show_name": "Lo Straordinario Mondo Di Gumball",
      "show_logo": "https://tv-programma.it/wp-content/uploads/2026/02/sample-image.webp",
      "start_time": "2026-02-15 04:40:00",
      "end_time": "2026-02-15 04:50:00",
      "episode_number": "S4 E5",
      "show_category": "Scoperta e avventura",
      "show_description": "Gumball è un simpatico gatto blu combina-guai che ogni giorno vive straordinarie avventure assieme a Darwin, l'amico pesciolino."
    },
    {
      "show_name": "Lo Straordinario Mondo Di Gumball",
      "show_logo": "https://tv-programma.it/wp-content/uploads/2026/02/sample-image.webp",
      "start_time": "2026-02-15 04:50:00",
      "end_time": "2026-02-15 05:00:00",
      "episode_number": "S4 E6",
      "show_category": "Scoperta e avventura",
      "show_description": "Gumball è un simpatico gatto blu combina-guai che ogni giorno vive straordinarie avventure assieme a Darwin, l'amico pesciolino."
    },
    {
      "show_name": "Lo Straordinario Mondo Di Gumball",
      "show_logo": "https://tv-programma.it/wp-content/uploads/2026/02/sample-image.webp",
      "start_time": "2026-02-15 05:00:00",
      "end_time": "2026-02-15 05:10:00",
      "episode_number": "S4 E7",
      "show_category": "Scoperta e avventura",
      "show_description": "Gumball è un simpatico gatto blu combina-guai che ogni giorno vive straordinarie avventure assieme a Darwin, l'amico pesciolino."
    },
    {
      "show_name": "Lo Straordinario Mondo Di Gumball",
      "show_logo": "https://tv-programma.it/wp-content/uploads/2026/02/sample-image.webp",
      "start_time": "2026-02-15 05:10:00",
      "end_time": "2026-02-15 05:20:00",
      "episode_number": "S4 E8",
      "show_category": "Scoperta e avventura",
      "show_description": "Gumball è un simpatico gatto blu combina-guai che ogni giorno vive straordinarie avventure assieme a Darwin, l'amico pesciolino."
    },
    {
      "show_name": "Lo Straordinario Mondo Di Gumball",
      "show_logo": "https://tv-programma.it/wp-content/uploads/2026/02/sample-image.webp",
      "start_time": "2026-02-15 05:20:00",
      "end_time": "2026-02-15 05:35:00",
      "episode_number": "S4 E9",
      "show_category": "Scoperta e avventura",
      "show_description": "Gumball è un simpatico gatto blu combina-guai che ogni giorno vive straordinarie avventure assieme a Darwin, l'amico pesciolino."
    },
    {
      "show_name": "Lo Straordinario Mondo Di Gumball",
      "show_logo": "https://tv-programma.it/wp-content/uploads/2026/02/sample-image.webp",
      "start_time": "2026-02-15 05:35:00",
      "end_time": "2026-02-15 05:45:00",
      "episode_number": "S4 E15",
      "show_category": "Scoperta e avventura",
      "show_description": "Gumball è un simpatico gatto blu combina-guai che ogni giorno vive straordinarie avventure assieme a Darwin, l'amico pesciolino."
    },
    {
      "show_name": "Lo Straordinario Mondo Di Gumball",
      "show_logo": "https://tv-programma.it/wp-content/uploads/2026/02/sample-image.webp",
      "start_time": "2026-02-15 05:45:00",
      "end_time": "2026-02-15 06:00:00",
      "episode_number": "S4 E16",
      "show_category": "Scoperta e avventura",
      "show_description": "Gumball è un simpatico gatto blu combina-guai che ogni giorno vive straordinarie avventure assieme a Darwin, l'amico pesciolino."
    },
    {
      "show_name": "Teen Titans Go!",
      "show_logo": "https://tv-programma.it/wp-content/uploads/2026/02/sample-image.webp",
      "start_time": "2026-02-15 06:00:00",
      "end_time": "2026-02-15 06:10:00",
      "episode_number": "S9 E17",
      "show_category": "Azione",
      "show_description": "I Teen Titans sono una squadra composta da cinque ragazzi che proteggono la Terra dalle forze del male."
    },
    {
      "show_name": "Teen Titans Go!",
      "show_logo": "https://tv-programma.it/wp-content/uploads/2026/02/sample-image.webp",
      "start_time": "2026-02-15 06:10:00",
      "end_time": "2026-02-15 06:20:00",
      "episode_number": "S9 E18",
      "show_category": "",
      "show_description": "C'e' un megalodonte affamato! I Titans accorrono e si rendono conto che quello squalo in realta' e' Don Jackson, famoso attore, trasformato in un pesce."
    },
    {
      "show_name": "Teen Titans Go!",
      "show_logo": "https://tv-programma.it/wp-content/uploads/2026/02/sample-image.webp",
      "start_time": "2026-02-15 06:20:00",
      "end_time": "2026-02-15 06:30:00",
      "episode_number": "S9 E13",
      "show_category": "",
      "show_description": "Il club del libro si riunisce! Ogni membro dei Teen Titans deve spiegare agli altri la storia del fumetto che ha letto durante la settimana, ma nessuno di loro l'ha fatto."
    },
    {
      "show_name": "Teen Titans Go!",
      "show_logo": "https://tv-programma.it/wp-content/uploads/2026/02/sample-image.webp",
      "start_time": "2026-02-15 06:30:00",
      "end_time": "2026-02-15 06:40:00",
      "episode_number": "S9 E20",
      "show_category": "Azione",
      "show_description": "I Teen Titans sono una squadra composta da cinque ragazzi che proteggono la Terra dalle forze del male."
    },
    {
      "show_name": "Teen Titans Go!",
      "show_logo": "https://tv-programma.it/wp-content/uploads/2026/02/sample-image.webp",
      "start_time": "2026-02-15 06:40:00",
      "end_time": "2026-02-15 06:50:00",
      "episode_number": "S9 E21",
      "show_category": "",
      "show_description": "Un gorilla dorme nella cucina dei Titans. Robin scopre dal telegiornale che e' fuggito dal parco. Il piano e' trasportarlo nel modo piu' silenzioso possibile allo zoo."
    },
    {
      "show_name": "Teen Titans Go!",
      "show_logo": "https://tv-programma.it/wp-content/uploads/2026/02/sample-image.webp",
      "start_time": "2026-02-15 06:50:00",
      "end_time": "2026-02-15 07:05:00",
      "episode_number": "S9 E23",
      "show_category": "",
      "show_description": "I Titans ricevono un volantino di un salone di bellezza dove fare la manicure e la pedicure. Robin all'inizio e' riluttante, ma presto ne sara' conquistato."
    },
    {
      "show_name": "New Looney Tunes",
      "show_logo": "https://tv-programma.it/wp-content/uploads/2026/02/sample-image.webp",
      "start_time": "2026-02-15 07:05:00",
      "end_time": "2026-02-15 07:15:00",
      "episode_number": "S3 E13",
      "show_category": "Scoperta e avventura",
      "show_description": "Bugs Bunny e' il protagonista di questa spassosissima serie animata. In ogni episodio intervengono anche altri personaggi, come Speedy Gonzales, gatto Silvestro e Titty."
    },
    {
      "show_name": "New Looney Tunes",
      "show_logo": "https://tv-programma.it/wp-content/uploads/2026/02/sample-image.webp",
      "start_time": "2026-02-15 07:15:00",
      "end_time": "2026-02-15 07:30:00",
      "episode_number": "S3 E14",
      "show_category": "Scoperta e avventura",
      "show_description": "Bugs Bunny e' il protagonista di questa spassosissima serie animata. In ogni episodio intervengono anche altri personaggi, come Speedy Gonzales, gatto Silvestro e Titty."
    },
    {
      "show_name": "New Looney Tunes",
      "show_logo": "https://tv-programma.it/wp-content/uploads/2026/02/sample-image.webp",
      "start_time": "2026-02-15 07:30:00",
      "end_time": "2026-02-15 07:40:00",
      "episode_number": "S3 E15",
      "show_category": "Scoperta e avventura",
      "show_description": "Bugs Bunny e' il protagonista di questa spassosissima serie animata. In ogni episodio intervengono anche altri personaggi, come Speedy Gonzales, gatto Silvestro e Titty."
    },
    {
      "show_name": "New Looney Tunes",
      "show_logo": "https://tv-programma.it/wp-content/uploads/2026/02/sample-image.webp",
      "start_time": "2026-02-15 07:40:00",
      "end_time": "2026-02-15 07:50:00",
      "episode_number": "S3 E16",
      "show_category": "Scoperta e avventura",
      "show_description": "Bugs Bunny e' il protagonista di questa spassosissima serie animata. In ogni episodio intervengono anche altri personaggi, come Speedy Gonzales, gatto Silvestro e Titty."
    },
    {
      "show_name": "Teen Titans Go!",
      "show_logo": "https://tv-programma.it/wp-content/uploads/2026/02/sample-image.webp",
      "start_time": "2026-02-15 07:50:00",
      "end_time": "2026-02-15 08:05:00",
      "episode_number": "S9 E8",
      "show_category": "Azione",
      "show_description": "I Teen Titans sono una squadra composta da cinque ragazzi che proteggono la Terra dalle forze del male."
    },
    {
      "show_name": "Teen Titans Go!",
      "show_logo": "https://tv-programma.it/wp-content/uploads/2026/02/sample-image.webp",
      "start_time": "2026-02-15 08:05:00",
      "end_time": "2026-02-15 08:15:00",
      "episode_number": "S9 E12",
      "show_category": "Azione",
      "show_description": "I Teen Titans sono una squadra composta da cinque ragazzi che proteggono la Terra dalle forze del male."
    },
    {
      "show_name": "Teen Titans Go!",
      "show_logo": "https://tv-programma.it/wp-content/uploads/2026/02/sample-image.webp",
      "start_time": "2026-02-15 08:15:00",
      "end_time": "2026-02-15 08:25:00",
      "episode_number": "S5 E44",
      "show_category": "",
      "show_description": "Il campo estivo e' finito. Birdarang consegna le medaglie di partecipazione a tutti i supereroi ma non ai Titans che sono stati troppo impegnati tra vicende sentimentali pirati e lupi."
    },
    {
      "show_name": "Teen Titans Go!",
      "show_logo": "https://tv-programma.it/wp-content/uploads/2026/02/sample-image.webp",
      "start_time": "2026-02-15 08:25:00",
      "end_time": "2026-02-15 08:35:00",
      "episode_number": "S9 E1",
      "show_category": "Azione",
      "show_description": "I Teen Titans sono una squadra composta da cinque ragazzi che proteggono la Terra dalle forze del male."
    },
    {
      "show_name": "Teen Titans Go!",
      "show_logo": "https://tv-programma.it/wp-content/uploads/2026/02/sample-image.webp",
      "start_time": "2026-02-15 08:35:00",
      "end_time": "2026-02-15 08:45:00",
      "episode_number": "S9 E2",
      "show_category": "Azione",
      "show_description": "I Teen Titans sono una squadra composta da cinque ragazzi che proteggono la Terra dalle forze del male."
    },
    {
      "show_name": "Teen Titans Go!",
      "show_logo": "https://tv-programma.it/wp-content/uploads/2026/02/sample-image.webp",
      "start_time": "2026-02-15 08:45:00",
      "end_time": "2026-02-15 08:55:00",
      "episode_number": "S9 E3",
      "show_category": "Azione",
      "show_description": "I Teen Titans sono una squadra composta da cinque ragazzi che proteggono la Terra dalle forze del male."
    },
    {
      "show_name": "Teen Titans Go!",
      "show_logo": "https://tv-programma.it/wp-content/uploads/2026/02/sample-image.webp",
      "start_time": "2026-02-15 08:55:00",
      "end_time": "2026-02-15 09:10:00",
      "episode_number": "S9 E4",
      "show_category": "Azione",
      "show_description": "I Teen Titans sono una squadra composta da cinque ragazzi che proteggono la Terra dalle forze del male."
    },
    {
      "show_name": "Teen Titans Go!",
      "show_logo": "https://tv-programma.it/wp-content/uploads/2026/02/sample-image.webp",
      "start_time": "2026-02-15 09:10:00",
      "end_time": "2026-02-15 09:20:00",
      "episode_number": "S9 E5",
      "show_category": "Azione",
      "show_description": "I Teen Titans sono una squadra composta da cinque ragazzi che proteggono la Terra dalle forze del male."
    },
    {
      "show_name": "Teen Titans Go!",
      "show_logo": "https://tv-programma.it/wp-content/uploads/2026/02/sample-image.webp",
      "start_time": "2026-02-15 09:20:00",
      "end_time": "2026-02-15 09:30:00",
      "episode_number": "S9 E6",
      "show_category": "Azione",
      "show_description": "I Teen Titans sono una squadra composta da cinque ragazzi che proteggono la Terra dalle forze del male."
    },
    {
      "show_name": "Teen Titans Go!",
      "show_logo": "https://tv-programma.it/wp-content/uploads/2026/02/sample-image.webp",
      "start_time": "2026-02-15 09:30:00",
      "end_time": "2026-02-15 09:40:00",
      "episode_number": "S9 E9",
      "show_category": "Azione",
      "show_description": "I Teen Titans sono una squadra composta da cinque ragazzi che proteggono la Terra dalle forze del male."
    },
    {
      "show_name": "Teen Titans Go!",
      "show_logo": "https://tv-programma.it/wp-content/uploads/2026/02/sample-image.webp",
      "start_time": "2026-02-15 09:40:00",
      "end_time": "2026-02-15 09:50:00",
      "episode_number": "S9 E10",
      "show_category": "Azione",
      "show_description": "I Teen Titans sono una squadra composta da cinque ragazzi che proteggono la Terra dalle forze del male."
    },
    {
      "show_name": "Teen Titans Go!",
      "show_logo": "https://tv-programma.it/wp-content/uploads/2026/02/sample-image.webp",
      "start_time": "2026-02-15 09:50:00",
      "end_time": "2026-02-15 10:05:00",
      "episode_number": "S9 E7",
      "show_category": "Azione",
      "show_description": "I Teen Titans sono una squadra composta da cinque ragazzi che proteggono la Terra dalle forze del male."
    },
    {
      "show_name": "Teen Titans Go!",
      "show_logo": "https://tv-programma.it/wp-content/uploads/2026/02/sample-image.webp",
      "start_time": "2026-02-15 10:05:00",
      "end_time": "2026-02-15 10:15:00",
      "episode_number": "S9 E11",
      "show_category": "Azione",
      "show_description": "I Teen Titans sono una squadra composta da cinque ragazzi che proteggono la Terra dalle forze del male."
    },
    {
      "show_name": "Teen Titans Go!",
      "show_logo": "https://tv-programma.it/wp-content/uploads/2026/02/sample-image.webp",
      "start_time": "2026-02-15 10:15:00",
      "end_time": "2026-02-15 10:25:00",
      "episode_number": "S6 E5",
      "show_category": "",
      "show_description": "Bibi sta con la sua famiglia, la Doom Patrol, quando lui, Robotman e Negative Girl decidono di andare a fare i ragazzacci e uscire con i granchi."
    },
    {
      "show_name": "Teen Titans Go!",
      "show_logo": "https://tv-programma.it/wp-content/uploads/2026/02/sample-image.webp",
      "start_time": "2026-02-15 10:25:00",
      "end_time": "2026-02-15 10:35:00",
      "episode_number": "S9 E19",
      "show_category": "Azione",
      "show_description": "I Teen Titans sono una squadra composta da cinque ragazzi che proteggono la Terra dalle forze del male."
    },
    {
      "show_name": "Teen Titans Go!",
      "show_logo": "https://tv-programma.it/wp-content/uploads/2026/02/sample-image.webp",
      "start_time": "2026-02-15 10:35:00",
      "end_time": "2026-02-15 10:45:00",
      "episode_number": "S9 E14",
      "show_category": "Azione",
      "show_description": "I Teen Titans sono una squadra composta da cinque ragazzi che proteggono la Terra dalle forze del male."
    },
    {
      "show_name": "Teen Titans Go!",
      "show_logo": "https://tv-programma.it/wp-content/uploads/2026/02/sample-image.webp",
      "start_time": "2026-02-15 10:45:00",
      "end_time": "2026-02-15 10:55:00",
      "episode_number": "S9 E15",
      "show_category": "Azione",
      "show_description": "I Teen Titans sono una squadra composta da cinque ragazzi che proteggono la Terra dalle forze del male."
    },
    {
      "show_name": "Teen Titans Go!",
      "show_logo": "https://tv-programma.it/wp-content/uploads/2026/02/sample-image.webp",
      "start_time": "2026-02-15 10:55:00",
      "end_time": "2026-02-15 11:10:00",
      "episode_number": "S9 E16",
      "show_category": "Azione",
      "show_description": "I Teen Titans sono una squadra composta da cinque ragazzi che proteggono la Terra dalle forze del male."
    },
    {
      "show_name": "Teen Titans Go!",
      "show_logo": "https://tv-programma.it/wp-content/uploads/2026/02/sample-image.webp",
      "start_time": "2026-02-15 11:10:00",
      "end_time": "2026-02-15 11:20:00",
      "episode_number": "S4 E4",
      "show_category": "Azione",
      "show_description": "I Teen Titans sono una squadra composta da cinque ragazzi che proteggono la Terra dalle forze del male."
    },
    {
      "show_name": "Teen Titans Go!",
      "show_logo": "https://tv-programma.it/wp-content/uploads/2026/02/sample-image.webp",
      "start_time": "2026-02-15 11:20:00",
      "end_time": "2026-02-15 11:30:00",
      "episode_number": "S4 E5",
      "show_category": "",
      "show_description": "Batman e Gordon fanno zapping in TV e guardano i Titans."
    },
    {
      "show_name": "Teen Titans Go!",
      "show_logo": "https://tv-programma.it/wp-content/uploads/2026/02/sample-image.webp",
      "start_time": "2026-02-15 11:30:00",
      "end_time": "2026-02-15 11:50:00",
      "episode_number": "S4 E6",
      "show_category": "",
      "show_description": "Bibi decide di festeggiare il suo compleanno con Stellarubia che non fa mai il compleanno perche' sulla Terra manca il giorno in cui e' nata ma se ne pente subito dopo."
    },
    {
      "show_name": "Teen Titans Go!",
      "show_logo": "https://tv-programma.it/wp-content/uploads/2026/02/sample-image.webp",
      "start_time": "2026-02-15 11:50:00",
      "end_time": "2026-02-15 11:55:00",
      "episode_number": "S4 E7",
      "show_category": "Azione",
      "show_description": "I Teen Titans sono una squadra composta da cinque ragazzi che proteggono la Terra dalle forze del male."
    },
    {
      "show_name": "Teen Titans Go!",
      "show_logo": "https://tv-programma.it/wp-content/uploads/2026/02/sample-image.webp",
      "start_time": "2026-02-15 11:55:00",
      "end_time": "2026-02-15 12:15:00",
      "episode_number": "S4 E8",
      "show_category": "Azione",
      "show_description": "I Teen Titans sono una squadra composta da cinque ragazzi che proteggono la Terra dalle forze del male."
    },
    {
      "show_name": "Teen Titans Go!",
      "show_logo": "https://tv-programma.it/wp-content/uploads/2026/02/sample-image.webp",
      "start_time": "2026-02-15 12:15:00",
      "end_time": "2026-02-15 12:25:00",
      "episode_number": "S4 E9",
      "show_category": "Azione",
      "show_description": "I Teen Titans sono una squadra composta da cinque ragazzi che proteggono la Terra dalle forze del male."
    },
    {
      "show_name": "Teen Titans Go!",
      "show_logo": "https://tv-programma.it/wp-content/uploads/2026/02/sample-image.webp",
      "start_time": "2026-02-15 12:25:00",
      "end_time": "2026-02-15 12:40:00",
      "episode_number": "S4 E10",
      "show_category": "Azione",
      "show_description": "I Teen Titans sono una squadra composta da cinque ragazzi che proteggono la Terra dalle forze del male."
    },
    {
      "show_name": "Clarence",
      "show_logo": "https://tv-programma.it/wp-content/uploads/downloaded-images/Boing/tomorrow/clarence.webp",
      "start_time": "2026-02-15 12:40:00",
      "end_time": "2026-02-15 12:50:00",
      "episode_number": "S3 E14",
      "show_category": "Commedia",
      "show_description": "La serie ruota intorno a Clarence Wendell, un bambino di 9 anni spensierato, entusiasta in maniera esagerata, comico, con qualche problema nel capire le cose, che prova a vedere il meglio in tutto ciò che lo circonda nonostante combini guai e risulti insopportabile quasi sempre."
    },
    {
      "show_name": "Clarence",
      "show_logo": "https://tv-programma.it/wp-content/uploads/downloaded-images/Boing/tomorrow/clarence.webp",
      "start_time": "2026-02-15 12:50:00",
      "end_time": "2026-02-15 13:00:00",
      "episode_number": "S4 E2",
      "show_category": "",
      "show_description": "Il gatto di Chelsea, Briciola,scappa di casa e la ragazzina, disperata, si fa aiutare da Clarence per ritrovarlo. I due amici vivono un'assurda avventura per trovarlo."
    },
    {
      "show_name": "Clarence",
      "show_logo": "https://tv-programma.it/wp-content/uploads/downloaded-images/Boing/tomorrow/clarence.webp",
      "start_time": "2026-02-15 13:00:00",
      "end_time": "2026-02-15 13:15:00",
      "episode_number": "S3 E15",
      "show_category": "Commedia",
      "show_description": "La serie ruota intorno a Clarence Wendell, un bambino di 9 anni spensierato, entusiasta in maniera esagerata, comico, con qualche problema nel capire le cose, che prova a vedere il meglio in tutto ciò che lo circonda nonostante combini guai e risulti insopportabile quasi sempre."
    },
    {
      "show_name": "Clarence",
      "show_logo": "https://tv-programma.it/wp-content/uploads/downloaded-images/Boing/tomorrow/clarence.webp",
      "start_time": "2026-02-15 13:15:00",
      "end_time": "2026-02-15 13:25:00",
      "episode_number": "S3 E16",
      "show_category": "Commedia",
      "show_description": "La serie ruota intorno a Clarence Wendell, un bambino di 9 anni spensierato, entusiasta in maniera esagerata, comico, con qualche problema nel capire le cose, che prova a vedere il meglio in tutto ciò che lo circonda nonostante combini guai e risulti insopportabile quasi sempre."
    },
    {
      "show_name": "Clarence",
      "show_logo": "https://tv-programma.it/wp-content/uploads/downloaded-images/Boing/tomorrow/clarence.webp",
      "start_time": "2026-02-15 13:25:00",
      "end_time": "2026-02-15 13:35:00",
      "episode_number": "S4 E3",
      "show_category": "",
      "show_description": "Il passato del signor Reese viene alla luce quando la sua ex collega della polizia l'agente Moody fa visita alla Scuola elementare Aberdale."
    },
    {
      "show_name": "Clarence",
      "show_logo": "https://tv-programma.it/wp-content/uploads/downloaded-images/Boing/tomorrow/clarence.webp",
      "start_time": "2026-02-15 13:35:00",
      "end_time": "2026-02-15 13:45:00",
      "episode_number": "S4 E4",
      "show_category": "",
      "show_description": "I baffetti di Gilben appena spuntati accendono una discussione sulla puberta'. Clarence capisce che e' giunto il momento di comportarsi da persona adulta."
    },
    {
      "show_name": "Clarence",
      "show_logo": "https://tv-programma.it/wp-content/uploads/downloaded-images/Boing/tomorrow/clarence.webp",
      "start_time": "2026-02-15 13:45:00",
      "end_time": "2026-02-15 13:55:00",
      "episode_number": "S1 E35",
      "show_category": "Commedia",
      "show_description": "La serie ruota intorno a Clarence Wendell, un bambino di 9 anni spensierato, entusiasta in maniera esagerata, comico, con qualche problema nel capire le cose, che prova a vedere il meglio in tutto ciò che lo circonda nonostante combini guai e risulti insopportabile quasi sempre."
    },
    {
      "show_name": "Clarence",
      "show_logo": "https://tv-programma.it/wp-content/uploads/downloaded-images/Boing/tomorrow/clarence.webp",
      "start_time": "2026-02-15 13:55:00",
      "end_time": "2026-02-15 14:10:00",
      "episode_number": "S4 E5",
      "show_category": "",
      "show_description": "Clarence conosce JT un ragazzo che porta il codino e ne resta affascinato. Per assomigliargli si fa pettinare come lui da sua madre."
    },
    {
      "show_name": "Clarence",
      "show_logo": "https://tv-programma.it/wp-content/uploads/downloaded-images/Boing/tomorrow/clarence.webp",
      "start_time": "2026-02-15 14:10:00",
      "end_time": "2026-02-15 14:20:00",
      "episode_number": "S4 E6",
      "show_category": "",
      "show_description": "Mentre Mary sbriga le sue commissioni Clarence aspetta in macchina e cerca di sconfiggere la noia."
    },
    {
      "show_name": "Clarence",
      "show_logo": "https://tv-programma.it/wp-content/uploads/downloaded-images/Boing/tomorrow/clarence.webp",
      "start_time": "2026-02-15 14:20:00",
      "end_time": "2026-02-15 14:30:00",
      "episode_number": "S3 E17",
      "show_category": "",
      "show_description": "I ragazzi vanno alla piscina comunale di Aberdale. Clarence cerca di evitare la bagnina per entrare nell'idromassaggio e preparare agli amici una sorpresa."
    },
    {
      "show_name": "Clarence",
      "show_logo": "https://tv-programma.it/wp-content/uploads/downloaded-images/Boing/tomorrow/clarence.webp",
      "start_time": "2026-02-15 14:30:00",
      "end_time": "2026-02-15 14:40:00",
      "episode_number": "S3 E18",
      "show_category": "",
      "show_description": "Mary iscrive Clarence al corso di Karate ma lui si annoia. Mary scoprira' quanto in realta' il Karate piaccia a lei e Clarence la sosterra' nella sua nuova passione."
    },
    {
      "show_name": "Clarence",
      "show_logo": "https://tv-programma.it/wp-content/uploads/downloaded-images/Boing/tomorrow/clarence.webp",
      "start_time": "2026-02-15 14:40:00",
      "end_time": "2026-02-15 14:55:00",
      "episode_number": "S4 E7",
      "show_category": "",
      "show_description": "Dopo aver ascoltato la radio durante la scuola, Clarence decide di fare una intervista a Sumo. La signora Baker la ascolta e gli propone un'intervista in diretta."
    },
    {
      "show_name": "Clarence",
      "show_logo": "https://tv-programma.it/wp-content/uploads/downloaded-images/Boing/tomorrow/clarence.webp",
      "start_time": "2026-02-15 14:55:00",
      "end_time": "2026-02-15 15:05:00",
      "episode_number": "S4 E8",
      "show_category": "",
      "show_description": "Clarence, Sumo e Jeff rompono la finestra di un vicino mentre giocano. Vanno a controllare i danni fatti e incontrano Lauren."
    },
    {
      "show_name": "Clarence",
      "show_logo": "https://tv-programma.it/wp-content/uploads/downloaded-images/Boing/tomorrow/clarence.webp",
      "start_time": "2026-02-15 15:05:00",
      "end_time": "2026-02-15 15:15:00",
      "episode_number": "S3 E19",
      "show_category": "Commedia",
      "show_description": "La serie ruota intorno a Clarence Wendell, un bambino di 9 anni spensierato, entusiasta in maniera esagerata, comico, con qualche problema nel capire le cose, che prova a vedere il meglio in tutto ciò che lo circonda nonostante combini guai e risulti insopportabile quasi sempre."
    },
    {
      "show_name": "Lo Straordinario Mondo Di Gumball",
      "show_logo": "https://tv-programma.it/wp-content/uploads/2026/02/sample-image.webp",
      "start_time": "2026-02-15 15:15:00",
      "end_time": "2026-02-15 15:30:00",
      "episode_number": "S2 E6",
      "show_category": "Scoperta e avventura",
      "show_description": "Gumball è un simpatico gatto blu combina-guai che ogni giorno vive straordinarie avventure assieme a Darwin, l'amico pesciolino."
    },
    {
      "show_name": "Lo Straordinario Mondo Di Gumball",
      "show_logo": "https://tv-programma.it/wp-content/uploads/2026/02/sample-image.webp",
      "start_time": "2026-02-15 15:30:00",
      "end_time": "2026-02-15 15:40:00",
      "episode_number": "S2 E6",
      "show_category": "Scoperta e avventura",
      "show_description": "Gumball è un simpatico gatto blu combina-guai che ogni giorno vive straordinarie avventure assieme a Darwin, l'amico pesciolino."
    },
    {
      "show_name": "Lo Straordinario Mondo Di Gumball",
      "show_logo": "https://tv-programma.it/wp-content/uploads/2026/02/sample-image.webp",
      "start_time": "2026-02-15 15:40:00",
      "end_time": "2026-02-15 15:50:00",
      "episode_number": "S2 E7",
      "show_category": "Scoperta e avventura",
      "show_description": "Gumball è un simpatico gatto blu combina-guai che ogni giorno vive straordinarie avventure assieme a Darwin, l'amico pesciolino."
    },
    {
      "show_name": "Lo Straordinario Mondo Di Gumball",
      "show_logo": "https://tv-programma.it/wp-content/uploads/2026/02/sample-image.webp",
      "start_time": "2026-02-15 15:50:00",
      "end_time": "2026-02-15 16:05:00",
      "episode_number": "S1 E5",
      "show_category": "",
      "show_description": "Gumball è un simpatico gatto blu combina-guai che ogni giorno vive straordinarie avventure assieme a Darwin, l'amico pesciolino."
    },
    {
      "show_name": "Lo Straordinario Mondo Di Gumball",
      "show_logo": "https://tv-programma.it/wp-content/uploads/2026/02/sample-image.webp",
      "start_time": "2026-02-15 16:05:00",
      "end_time": "2026-02-15 16:15:00",
      "episode_number": "S2 E7",
      "show_category": "Scoperta e avventura",
      "show_description": "Gumball è un simpatico gatto blu combina-guai che ogni giorno vive straordinarie avventure assieme a Darwin, l'amico pesciolino."
    },
    {
      "show_name": "Lo Straordinario Mondo Di Gumball",
      "show_logo": "https://tv-programma.it/wp-content/uploads/2026/02/sample-image.webp",
      "start_time": "2026-02-15 16:15:00",
      "end_time": "2026-02-15 16:25:00",
      "episode_number": "S2 E8",
      "show_category": "Scoperta e avventura",
      "show_description": "Gumball è un simpatico gatto blu combina-guai che ogni giorno vive straordinarie avventure assieme a Darwin, l'amico pesciolino."
    },
    {
      "show_name": "Lo Straordinario Mondo Di Gumball",
      "show_logo": "https://tv-programma.it/wp-content/uploads/2026/02/sample-image.webp",
      "start_time": "2026-02-15 16:25:00",
      "end_time": "2026-02-15 16:40:00",
      "episode_number": "S2 E8",
      "show_category": "Scoperta e avventura",
      "show_description": "Gumball è un simpatico gatto blu combina-guai che ogni giorno vive straordinarie avventure assieme a Darwin, l'amico pesciolino."
    },
    {
      "show_name": "Lo Straordinario Mondo Di Gumball",
      "show_logo": "https://tv-programma.it/wp-content/uploads/2026/02/sample-image.webp",
      "start_time": "2026-02-15 16:40:00",
      "end_time": "2026-02-15 16:50:00",
      "episode_number": "S2 E9",
      "show_category": "Scoperta e avventura",
      "show_description": "Gumball è un simpatico gatto blu combina-guai che ogni giorno vive straordinarie avventure assieme a Darwin, l'amico pesciolino."
    },
    {
      "show_name": "Lo Straordinario Mondo Di Gumball",
      "show_logo": "https://tv-programma.it/wp-content/uploads/2026/02/sample-image.webp",
      "start_time": "2026-02-15 16:50:00",
      "end_time": "2026-02-15 17:05:00",
      "episode_number": "S2 E9",
      "show_category": "Scoperta e avventura",
      "show_description": "Gumball è un simpatico gatto blu combina-guai che ogni giorno vive straordinarie avventure assieme a Darwin, l'amico pesciolino."
    },
    {
      "show_name": "Lo Straordinario Mondo Di Gumball",
      "show_logo": "https://tv-programma.it/wp-content/uploads/2026/02/sample-image.webp",
      "start_time": "2026-02-15 17:05:00",
      "end_time": "2026-02-15 17:20:00",
      "episode_number": "S2 E10",
      "show_category": "Scoperta e avventura",
      "show_description": "Gumball è un simpatico gatto blu combina-guai che ogni giorno vive straordinarie avventure assieme a Darwin, l'amico pesciolino."
    },
    {
      "show_name": "Lo Straordinario Mondo Di Gumball",
      "show_logo": "https://tv-programma.it/wp-content/uploads/2026/02/sample-image.webp",
      "start_time": "2026-02-15 17:20:00",
      "end_time": "2026-02-15 17:30:00",
      "episode_number": "S2 E10",
      "show_category": "Scoperta e avventura",
      "show_description": "Gumball è un simpatico gatto blu combina-guai che ogni giorno vive straordinarie avventure assieme a Darwin, l'amico pesciolino."
    },
    {
      "show_name": "Lo Straordinario Mondo Di Gumball",
      "show_logo": "https://tv-programma.it/wp-content/uploads/2026/02/sample-image.webp",
      "start_time": "2026-02-15 17:30:00",
      "end_time": "2026-02-15 17:45:00",
      "episode_number": "S2 E11",
      "show_category": "Scoperta e avventura",
      "show_description": "Gumball è un simpatico gatto blu combina-guai che ogni giorno vive straordinarie avventure assieme a Darwin, l'amico pesciolino."
    },
    {
      "show_name": "Lo Straordinario Mondo Di Gumball",
      "show_logo": "https://tv-programma.it/wp-content/uploads/2026/02/sample-image.webp",
      "start_time": "2026-02-15 17:45:00",
      "end_time": "2026-02-15 17:55:00",
      "episode_number": "S4 E8",
      "show_category": "Scoperta e avventura",
      "show_description": "Gumball è un simpatico gatto blu combina-guai che ogni giorno vive straordinarie avventure assieme a Darwin, l'amico pesciolino."
    },
    {
      "show_name": "Lo Straordinario Mondo Di Gumball",
      "show_logo": "https://tv-programma.it/wp-content/uploads/2026/02/sample-image.webp",
      "start_time": "2026-02-15 17:55:00",
      "end_time": "2026-02-15 18:15:00",
      "episode_number": "S4 E12",
      "show_category": "Scoperta e avventura",
      "show_description": "Gumball è un simpatico gatto blu combina-guai che ogni giorno vive straordinarie avventure assieme a Darwin, l'amico pesciolino."
    },
    {
      "show_name": "Lo Straordinario Mondo Di Gumball",
      "show_logo": "https://tv-programma.it/wp-content/uploads/2026/02/sample-image.webp",
      "start_time": "2026-02-15 18:15:00",
      "end_time": "2026-02-15 18:25:00",
      "episode_number": "S3 E5",
      "show_category": "Scoperta e avventura",
      "show_description": "Gumball è un simpatico gatto blu combina-guai che ogni giorno vive straordinarie avventure assieme a Darwin, l'amico pesciolino."
    },
    {
      "show_name": "Lo Straordinario Mondo Di Gumball",
      "show_logo": "https://tv-programma.it/wp-content/uploads/2026/02/sample-image.webp",
      "start_time": "2026-02-15 18:25:00",
      "end_time": "2026-02-15 18:45:00",
      "episode_number": "S3 E9",
      "show_category": "Scoperta e avventura",
      "show_description": "Gumball è un simpatico gatto blu combina-guai che ogni giorno vive straordinarie avventure assieme a Darwin, l'amico pesciolino."
    },
    {
      "show_name": "Lo Straordinario Mondo Di Gumball",
      "show_logo": "https://tv-programma.it/wp-content/uploads/2026/02/sample-image.webp",
      "start_time": "2026-02-15 18:45:00",
      "end_time": "2026-02-15 18:55:00",
      "episode_number": "S5 E7",
      "show_category": "Scoperta e avventura",
      "show_description": "Gumball è un simpatico gatto blu combina-guai che ogni giorno vive straordinarie avventure assieme a Darwin, l'amico pesciolino."
    },
    {
      "show_name": "Lo Straordinario Mondo Di Gumball",
      "show_logo": "https://tv-programma.it/wp-content/uploads/2026/02/sample-image.webp",
      "start_time": "2026-02-15 18:55:00",
      "end_time": "2026-02-15 19:10:00",
      "episode_number": "S5 E21",
      "show_category": "Scoperta e avventura",
      "show_description": "Gumball è un simpatico gatto blu combina-guai che ogni giorno vive straordinarie avventure assieme a Darwin, l'amico pesciolino."
    },
    {
      "show_name": "Lo Straordinario Mondo Di Gumball",
      "show_logo": "https://tv-programma.it/wp-content/uploads/2026/02/sample-image.webp",
      "start_time": "2026-02-15 19:10:00",
      "end_time": "2026-02-15 19:20:00",
      "episode_number": "S2 E11",
      "show_category": "Scoperta e avventura",
      "show_description": "Gumball è un simpatico gatto blu combina-guai che ogni giorno vive straordinarie avventure assieme a Darwin, l'amico pesciolino."
    },
    {
      "show_name": "Lo Straordinario Mondo Di Gumball",
      "show_logo": "https://tv-programma.it/wp-content/uploads/2026/02/sample-image.webp",
      "start_time": "2026-02-15 19:20:00",
      "end_time": "2026-02-15 19:35:00",
      "episode_number": "S2 E12",
      "show_category": "Scoperta e avventura",
      "show_description": "Gumball è un simpatico gatto blu combina-guai che ogni giorno vive straordinarie avventure assieme a Darwin, l'amico pesciolino."
    },
    {
      "show_name": "Lo Straordinario Mondo Di Gumball",
      "show_logo": "https://tv-programma.it/wp-content/uploads/2026/02/sample-image.webp",
      "start_time": "2026-02-15 19:35:00",
      "end_time": "2026-02-15 19:50:00",
      "episode_number": "S2 E12",
      "show_category": "Scoperta e avventura",
      "show_description": "Gumball è un simpatico gatto blu combina-guai che ogni giorno vive straordinarie avventure assieme a Darwin, l'amico pesciolino."
    },
    {
      "show_name": "Lo Straordinario Mondo Di Gumball",
      "show_logo": "https://tv-programma.it/wp-content/uploads/2026/02/sample-image.webp",
      "start_time": "2026-02-15 19:50:00",
      "end_time": "2026-02-15 20:00:00",
      "episode_number": "S6 E3",
      "show_category": "Scoperta e avventura",
      "show_description": "Gumball è un simpatico gatto blu combina-guai che ogni giorno vive straordinarie avventure assieme a Darwin, l'amico pesciolino."
    },
    {
      "show_name": "Lo Straordinario Mondo Di Gumball",
      "show_logo": "https://tv-programma.it/wp-content/uploads/2026/02/sample-image.webp",
      "start_time": "2026-02-15 20:00:00",
      "end_time": "2026-02-15 20:15:00",
      "episode_number": "S6 E4",
      "show_category": "Scoperta e avventura",
      "show_description": "Gumball è un simpatico gatto blu combina-guai che ogni giorno vive straordinarie avventure assieme a Darwin, l'amico pesciolino."
    },
    {
      "show_name": "Lo Straordinario Mondo Di Gumball",
      "show_logo": "https://tv-programma.it/wp-content/uploads/2026/02/sample-image.webp",
      "start_time": "2026-02-15 20:15:00",
      "end_time": "2026-02-15 20:25:00",
      "episode_number": "S6 E5",
      "show_category": "Scoperta e avventura",
      "show_description": "Gumball è un simpatico gatto blu combina-guai che ogni giorno vive straordinarie avventure assieme a Darwin, l'amico pesciolino."
    },
    {
      "show_name": "Lo Straordinario Mondo Di Gumball",
      "show_logo": "https://tv-programma.it/wp-content/uploads/2026/02/sample-image.webp",
      "start_time": "2026-02-15 20:25:00",
      "end_time": "2026-02-15 20:35:00",
      "episode_number": "S6 E6",
      "show_category": "Scoperta e avventura",
      "show_description": "Gumball è un simpatico gatto blu combina-guai che ogni giorno vive straordinarie avventure assieme a Darwin, l'amico pesciolino."
    },
    {
      "show_name": "Lo Straordinario Mondo Di Gumball",
      "show_logo": "https://tv-programma.it/wp-content/uploads/2026/02/sample-image.webp",
      "start_time": "2026-02-15 20:35:00",
      "end_time": "2026-02-15 20:50:00",
      "episode_number": "S6 E39",
      "show_category": "Scoperta e avventura",
      "show_description": "Gumball è un simpatico gatto blu combina-guai che ogni giorno vive straordinarie avventure assieme a Darwin, l'amico pesciolino."
    },
    {
      "show_name": "Lo Straordinario Mondo Di Gumball",
      "show_logo": "https://tv-programma.it/wp-content/uploads/2026/02/sample-image.webp",
      "start_time": "2026-02-15 20:50:00",
      "end_time": "2026-02-15 21:00:00",
      "episode_number": "S6 E40",
      "show_category": "Scoperta e avventura",
      "show_description": "Gumball è un simpatico gatto blu combina-guai che ogni giorno vive straordinarie avventure assieme a Darwin, l'amico pesciolino."
    },
    {
      "show_name": "Lo Straordinario Mondo Di Gumball",
      "show_logo": "https://tv-programma.it/wp-content/uploads/2026/02/sample-image.webp",
      "start_time": "2026-02-15 21:00:00",
      "end_time": "2026-02-15 21:15:00",
      "episode_number": "S6 E41",
      "show_category": "Scoperta e avventura",
      "show_description": "Gumball è un simpatico gatto blu combina-guai che ogni giorno vive straordinarie avventure assieme a Darwin, l'amico pesciolino."
    },
    {
      "show_name": "Lo Straordinario Mondo Di Gumball",
      "show_logo": "https://tv-programma.it/wp-content/uploads/2026/02/sample-image.webp",
      "start_time": "2026-02-15 21:15:00",
      "end_time": "2026-02-15 21:25:00",
      "episode_number": "S6 E43",
      "show_category": "Scoperta e avventura",
      "show_description": "Gumball è un simpatico gatto blu combina-guai che ogni giorno vive straordinarie avventure assieme a Darwin, l'amico pesciolino."
    },
    {
      "show_name": "Lo Straordinario Mondo Di Gumball",
      "show_logo": "https://tv-programma.it/wp-content/uploads/2026/02/sample-image.webp",
      "start_time": "2026-02-15 21:25:00",
      "end_time": "2026-02-15 21:45:00",
      "episode_number": "S6 E44",
      "show_category": "Scoperta e avventura",
      "show_description": "Gumball è un simpatico gatto blu combina-guai che ogni giorno vive straordinarie avventure assieme a Darwin, l'amico pesciolino."
    },
    {
      "show_name": "Dragon Ball Super",
      "show_logo": "https://tv-programma.it/wp-content/uploads/2026/02/sample-image.webp",
      "start_time": "2026-02-15 21:45:00",
      "end_time": "2026-02-15 22:15:00",
      "episode_number": "S1 E84",
      "show_category": "Anime",
      "show_description": "Goku e Gohan vanno da Crili e C-18 per invitarli a prendere parte al torneo."
    },
    {
      "show_name": "Dragon Ball Super",
      "show_logo": "https://tv-programma.it/wp-content/uploads/2026/02/sample-image.webp",
      "start_time": "2026-02-15 22:15:00",
      "end_time": "2026-02-15 22:45:00",
      "episode_number": "S1 E85",
      "show_category": "Anime",
      "show_description": "Gohan raggiunge Junior per allenarsi mentre Goku va alla ricerca di C-17, con l'aiuto di Dende."
    },
    {
      "show_name": "Captain Tsubasa",
      "show_logo": "https://tv-programma.it/wp-content/uploads/downloaded-images/Boing/tomorrow/captain-tsubasa.webp",
      "start_time": "2026-02-15 22:45:00",
      "end_time": "2026-02-15 23:15:00",
      "episode_number": "S1 E38",
      "show_category": "Anime",
      "show_description": "La tecnica di Kazuo e Masao è molto stancante per le gambe quindi la usano con parsimonia."
    },
    {
      "show_name": "Captain Tsubasa",
      "show_logo": "https://tv-programma.it/wp-content/uploads/downloaded-images/Boing/tomorrow/captain-tsubasa.webp",
      "start_time": "2026-02-15 23:15:00",
      "end_time": "2026-02-15 23:45:00",
      "episode_number": "S1 E39",
      "show_category": "Anime",
      "show_description": "La quarta partita dei quarti di finale è tra la Newteam e la Hirado. La partita inizia in salita per i favoriti che dopo pochi minuti perdono già per 2-0."
    },
    {
      "show_name": "Lo Straordinario Mondo Di Gumball",
      "show_logo": "https://tv-programma.it/wp-content/uploads/2026/02/sample-image.webp",
      "start_time": "2026-02-15 23:45:00",
      "end_time": "2026-02-15 23:55:00",
      "episode_number": "S4 E17",
      "show_category": "Scoperta e avventura",
      "show_description": "Gumball è un simpatico gatto blu combina-guai che ogni giorno vive straordinarie avventure assieme a Darwin, l'amico pesciolino."
    },
    {
      "show_name": "Lo Straordinario Mondo Di Gumball",
      "show_logo": "https://tv-programma.it/wp-content/uploads/2026/02/sample-image.webp",
      "start_time": "2026-02-15 23:55:00",
      "end_time": "2026-02-16 00:05:00",
      "episode_number": "S4 E19",
      "show_category": "Scoperta e avventura",
      "show_description": "Gumball è un simpatico gatto blu combina-guai che ogni giorno vive straordinarie avventure assieme a Darwin, l'amico pesciolino."
    }
  ]
}