{
  "channel_name": "Sky Sport  256",
  "date": "2026-02-11",
  "programs": [
    {
      "show_name": "Foggia - Picerno",
      "show_logo": "https://guidatv.sky.it/uuid/5d58a4ad-f7c9-40d3-a7f2-9943cc8df905/cover?territory=IT&md5ChecksumParam=4fdae6d809473ec9951f2a25205319cb",
      "start_time": "2026-02-11 00:00:00",
      "end_time": "2026-02-11 20:00:00",
      "episode_number": "S2025 E266",
      "show_category": "Sport",
      "show_description": "Dallo Stadio Pino Zaccheria di Foggia, Italia."
    },
    {
      "show_name": "Arzignano Valchiampo - Trento",
      "show_logo": "https://guidatv.sky.it/uuid/7a12988f-2094-46bf-b08e-b8ebe1c9d8d7/cover?territory=IT&md5ChecksumParam=dc958ef398317779d24a9687acf174f0",
      "start_time": "2026-02-11 20:00:00",
      "end_time": "2026-02-12 20:00:00",
      "episode_number": "S2025 E262",
      "show_category": "Sport",
      "show_description": "Dallo stadio Tommaso Dal Molin in Veneto, Italia."
    }
  ]
}