{
  "channel_name": "TV8 HD",
  "date": "2026-02-15",
  "programs": [
    {
      "show_name": "Alessandro Borghese - 4 Ristoranti",
      "show_logo": "https://tv-programma.it/wp-content/uploads/downloaded-images/TV8-HD/tomorrow/alessandro-borghese-4-ristoranti.webp",
      "start_time": "2026-02-15 00:00:00",
      "end_time": "2026-02-15 01:00:00",
      "episode_number": "S5 E11",
      "show_category": "Intrattenimento",
      "show_description": "Lungo la costa da San Felice Circeo al Golfo di Gaeta chi tra Rossella, Silvia, Andrea e Massimo si aggiudichera' il titolo di miglior ristorante gestito da marito e moglie?"
    },
    {
      "show_name": "Paradiso amaro",
      "show_logo": "https://tv-programma.it/wp-content/uploads/downloaded-images/TV8-HD/tomorrow/paradiso-amaro.webp",
      "start_time": "2026-02-15 01:00:00",
      "end_time": "2026-02-15 03:10:00",
      "episode_number": "",
      "show_category": "Film",
      "show_description": "Oscar alla sceneggiatura e due Golden Globe per una commedia ambientata alle Hawaii con George Clooney. Matt King, sposato con due figlie per le quali è sempre stato il 'secondo' genitore, ha dedicato le sue giornate più alla carriera di avvocato che alla propria famiglia. Quando però la moglie entra in coma, dopo un incidente in barca, Matt torna a prendersi cura delle ragazze e scopre che la donna aveva una relazione clandestina. Insieme alle figlie, attraversa tutto l'arcipelago per conoscere il suo rivale. Dal regista di \"Sideways - In viaggio con Jack\"."
    },
    {
      "show_name": "Lady Killer",
      "show_logo": "https://tv-programma.it/wp-content/uploads/downloaded-images/TV8-HD/tomorrow/lady-killer.webp",
      "start_time": "2026-02-15 03:10:00",
      "end_time": "2026-02-15 04:10:00",
      "episode_number": "S22 E18",
      "show_category": "Intrattenimento",
      "show_description": "Ep18 - Sono delicate, generose, vanitose ed innamorate, ma quando vengono ferite diventano vendicative e pericolose. In ogni episodio affrontiamo il caso di una donna diventata di colpo una feroce assassina."
    },
    {
      "show_name": "Coppie che uccidono",
      "show_logo": "https://tv-programma.it/wp-content/uploads/downloaded-images/TV8-HD/tomorrow/coppie-che-uccidono.webp",
      "start_time": "2026-02-15 04:10:00",
      "end_time": "2026-02-15 05:10:00",
      "episode_number": "S17 E20",
      "show_category": "Intrattenimento",
      "show_description": "Coppie che uccidono."
    },
    {
      "show_name": "Lady Killer",
      "show_logo": "https://tv-programma.it/wp-content/uploads/downloaded-images/TV8-HD/tomorrow/lady-killer.webp",
      "start_time": "2026-02-15 05:10:00",
      "end_time": "2026-02-15 06:00:00",
      "episode_number": "S22 E1",
      "show_category": "Mondo e Tendenze",
      "show_description": "S22 Ep1 - Sono delicate, generose, vanitose ed innamorate, ma quando vengono ferite diventano vendicative e pericolose. In ogni episodio affrontiamo il caso di una donna diventata di colpo una feroce assassina."
    },
    {
      "show_name": "TG24 mezz'ora",
      "show_logo": "https://tv-programma.it/wp-content/uploads/downloaded-images/TV8-HD/tomorrow/tg24-mezz-ora.webp",
      "start_time": "2026-02-15 06:00:00",
      "end_time": "2026-02-15 06:30:00",
      "episode_number": "",
      "show_category": "Informazione",
      "show_description": "Telegiornale in diretta. I giornali di oggi, lo Sport, il Meteo."
    },
    {
      "show_name": "TG24 mezz'ora",
      "show_logo": "https://tv-programma.it/wp-content/uploads/downloaded-images/TV8-HD/tomorrow/tg24-mezz-ora.webp",
      "start_time": "2026-02-15 06:30:00",
      "end_time": "2026-02-15 06:55:00",
      "episode_number": "",
      "show_category": "Informazione",
      "show_description": "Telegiornale in diretta. I giornali di oggi, lo Sport, il Meteo."
    },
    {
      "show_name": "TG24 Preview",
      "show_logo": "https://tv-programma.it/wp-content/uploads/downloaded-images/TV8-HD/tomorrow/tg24-preview.webp",
      "start_time": "2026-02-15 06:55:00",
      "end_time": "2026-02-15 07:00:00",
      "episode_number": "",
      "show_category": "Informazione",
      "show_description": "TG24 Preview."
    },
    {
      "show_name": "TG24 mezz'ora",
      "show_logo": "https://tv-programma.it/wp-content/uploads/downloaded-images/TV8-HD/tomorrow/tg24-mezz-ora.webp",
      "start_time": "2026-02-15 07:00:00",
      "end_time": "2026-02-15 07:20:00",
      "episode_number": "",
      "show_category": "Informazione",
      "show_description": "Telegiornale in diretta. I giornali di oggi, lo Sport, il Meteo."
    },
    {
      "show_name": "Sky Meteo24",
      "show_logo": "https://tv-programma.it/wp-content/uploads/downloaded-images/TV8-HD/tomorrow/sky-meteo24.webp",
      "start_time": "2026-02-15 07:20:00",
      "end_time": "2026-02-15 07:30:00",
      "episode_number": "",
      "show_category": "Informazione",
      "show_description": "Previsioni meteo dettagliate e sempre aggiornate 24 ore al giorno. Le previsioni regionali, nazionali ed internazionali."
    },
    {
      "show_name": "Consigli di San Valentino",
      "show_logo": "https://tv-programma.it/wp-content/uploads/downloaded-images/TV8-HD/tomorrow/consigli-di-san-valentino.webp",
      "start_time": "2026-02-15 07:30:00",
      "end_time": "2026-02-15 09:15:00",
      "episode_number": "",
      "show_category": "Film",
      "show_description": "Una blogger specializzata in tormenti amorosi si innamora di un fascinoso veterinario ma scopre che e' uno dei suoi piu' accaniti 'haters'."
    },
    {
      "show_name": "Sky TG24 in pillole",
      "show_logo": "https://tv-programma.it/wp-content/uploads/downloaded-images/TV8-HD/tomorrow/sky-tg24-in-pillole.webp",
      "start_time": "2026-02-15 09:15:00",
      "end_time": "2026-02-15 09:20:00",
      "episode_number": "",
      "show_category": "Informazione",
      "show_description": "Il telegiornale con le notizie piu' importanti del giorno."
    },
    {
      "show_name": "La nostra storia",
      "show_logo": "https://tv-programma.it/wp-content/uploads/downloaded-images/TV8-HD/tomorrow/la-nostra-storia.webp",
      "start_time": "2026-02-15 09:20:00",
      "end_time": "2026-02-15 11:05:00",
      "episode_number": "",
      "show_category": "Film",
      "show_description": "Per salvare la piccola libreria di cui e' proprietaria, Jamie deve entrare in conflitto con il suo ex fidanzato architetto."
    },
    {
      "show_name": "Sky TG24 in pillole",
      "show_logo": "https://tv-programma.it/wp-content/uploads/downloaded-images/TV8-HD/tomorrow/sky-tg24-in-pillole.webp",
      "start_time": "2026-02-15 11:05:00",
      "end_time": "2026-02-15 11:10:00",
      "episode_number": "",
      "show_category": "Informazione",
      "show_description": "Il telegiornale con le notizie piu' importanti del giorno."
    },
    {
      "show_name": "Bruno Barbieri - 4 Hotel",
      "show_logo": "https://tv-programma.it/wp-content/uploads/downloaded-images/TV8-HD/tomorrow/bruno-barbieri-4-hotel.webp",
      "start_time": "2026-02-15 11:10:00",
      "end_time": "2026-02-15 12:30:00",
      "episode_number": "S7 E8",
      "show_category": "Intrattenimento",
      "show_description": "Bruno Barbieri arriva in Trentino per godersi un soggiorno romantico. Tra spa private, cene a lume di candela e dolci sorprese, le montagne accoglieranno tutti gli innamorati."
    },
    {
      "show_name": "Alessandro Borghese - 4 Ristoranti...",
      "show_logo": "https://tv-programma.it/wp-content/uploads/downloaded-images/TV8-HD/tomorrow/alessandro-borghese-4-ristoranti.webp",
      "start_time": "2026-02-15 12:30:00",
      "end_time": "2026-02-15 13:40:00",
      "episode_number": "S3 E7",
      "show_category": "Intrattenimento",
      "show_description": "Il trullo e' senza dubbio il simbolo della Puglia e Alessandro Borghese, in questa puntata, vuole assaggiare la cucina tipica pugliese e trovare il miglior ristorante in un trullo."
    },
    {
      "show_name": "Un pizzico d'amore",
      "show_logo": "https://tv-programma.it/wp-content/uploads/downloaded-images/TV8-HD/tomorrow/un-pizzico-d-amore.webp",
      "start_time": "2026-02-15 13:40:00",
      "end_time": "2026-02-15 15:25:00",
      "episode_number": "",
      "show_category": "Film",
      "show_description": "Nikki e' un'aspirante chef ingaggiata nel ristorante di Holly Hanson, famosa regina dei fornelli. Ma Nikki cambiera' idea sulla donna che ha sempre idolatrato."
    },
    {
      "show_name": "Più dolce del cioccolato",
      "show_logo": "https://tv-programma.it/wp-content/uploads/downloaded-images/TV8-HD/tomorrow/pi-dolce-del-cioccolato.webp",
      "start_time": "2026-02-15 15:25:00",
      "end_time": "2026-02-15 17:10:00",
      "episode_number": "",
      "show_category": "Film",
      "show_description": "Si dice che una cioccolatiera locale abbia la ricetta segreta per trovare il vero amore a San Valentino, spingendo un giornalista televisivo ad indagare."
    },
    {
      "show_name": "Un amore inaspettato",
      "show_logo": "https://tv-programma.it/wp-content/uploads/downloaded-images/TV8-HD/tomorrow/un-amore-inaspettato.webp",
      "start_time": "2026-02-15 17:10:00",
      "end_time": "2026-02-15 18:55:00",
      "episode_number": "",
      "show_category": "Film",
      "show_description": "Chiamati a fare da testimoni alle nozze dei loro amici, Nick e Molly scoprono di avere la giusta alchimia ma c'e' un piccolo problema: sono entrambi gia' impegnati..."
    },
    {
      "show_name": "Alessandro Borghese - 4 Ristoranti",
      "show_logo": "https://tv-programma.it/wp-content/uploads/downloaded-images/TV8-HD/tomorrow/alessandro-borghese-4-ristoranti.webp",
      "start_time": "2026-02-15 18:55:00",
      "end_time": "2026-02-15 20:05:00",
      "episode_number": "S5 E4",
      "show_category": "Intrattenimento",
      "show_description": "Laura, Sanzio, Lorenzo e Nicolo' accompagnano Alessandro alla scoperta del Monferrato, terra piemontese di vini, storia e buon cibo. Quale sara' il menu' che conquistera' Alessandro?"
    },
    {
      "show_name": "Alessandro Borghese - 4 Ristoranti",
      "show_logo": "https://tv-programma.it/wp-content/uploads/downloaded-images/TV8-HD/tomorrow/alessandro-borghese-4-ristoranti.webp",
      "start_time": "2026-02-15 20:05:00",
      "end_time": "2026-02-15 21:35:00",
      "episode_number": "S8 E13",
      "show_category": "Intrattenimento",
      "show_description": "Al Pigneto, lo spirito romano incontra la fervente modernita'. Alessandro torna nella capitale: parte la sfida tra Luca, Gioia, Romina e Diego!"
    },
    {
      "show_name": "Infinite Storm",
      "show_logo": "https://tv-programma.it/wp-content/uploads/downloaded-images/TV8-HD/tomorrow/infinite-storm.webp",
      "start_time": "2026-02-15 21:35:00",
      "end_time": "2026-02-15 23:25:00",
      "episode_number": "",
      "show_category": "Film",
      "show_description": "Naomi Watts in un survival drama da una storia vera. Una scalatrice si arrampica sul monte Washington, ma una tormenta la costringe a tornare indietro mentre la notte si avvicina."
    },
    {
      "show_name": "Now you see me - I maghi del crimine",
      "show_logo": "https://tv-programma.it/wp-content/uploads/downloaded-images/TV8-HD/tomorrow/now-you-see-me-i-maghi-del-crimine.webp",
      "start_time": "2026-02-15 23:25:00",
      "end_time": "2026-02-16 01:25:00",
      "episode_number": "",
      "show_category": "Film",
      "show_description": "Illusionismo e colpi di scena in un thriller con Jesse Eisenberg, Mark Ruffalo e Morgan Freeman. Quattro maghi inscenano spettacolari trucchi di magia, sempre connessi a giganteschi furti."
    }
  ]
}